{"errors":{},"id":3738802,"source_code":"DMDRN","source_name":"Damodaran Financial Data","code":"AMM_TO_ALLFINANCIALRATIOS","name":"Almaden Minerals Ltd ( AMM.TO ) - All Financial Ratios","urlize_name":"Almaden-Minerals-Ltd-AMM-TO-All-Financial-Ratios","description":"Corporate Finance data is collected and calculated by Prof. Aswath\nDamodaran, Professor of Finance at the Stern School of Business, New\nYork University.  The raw data is available here:\nhttp://pages.stern.nyu.edu/~adamodar/New_Home_Page/data.html","updated_at":"2014-03-14T01:19:04Z","frequency":"annual","from_date":"2007-12-31","to_date":"2012-12-31","column_names":["Date","Number of Shares Outstanding","3-Year Regression Beta","3-year Standard Deviation of Stock Price","Book Value of Equity","Book Value of Assets","Capital Expenditures","Cash","Correlation with the Market","Depreciation","Dividends","Earnings Before Interest and Taxes","EBIT for Previous Period","Earnings Before Interest Taxes Depreciation and Amortization","Effective Tax Rate","Enterprise Value","EV to Trailing Sales Ratio","Firm Value","Hi-Lo Risk","Institutional Holdings","Invested Capital","Market Capitalization","Net Income","Non-Cash Working Capital","Reinvestment Amount","Sales General and Administration Expenses","Stock Price","Total Debt","Trading Volume","Trailing 12-month Revenues","Trailing Net Income","Trailing Revenues","Value Line Beta"],"private":false,"type":null,"display_url":"http://pages.stern.nyu.edu/~adamodar/New_Home_Page/data.html","data":[["2012-12-31",0.0,0.16,1.0267,null,null,0.0,0.0,0.04,0.0,0.0,null,null,null,0.0,0.0,0.0,0.0,0.3593,0.1102,null,0.0,0.0,0.0,0.0,0.0,3.18,0.0,10911.0,1.4,-2.2,1.4,1.05],["2009-12-31",0.0,0.06,0.7962,null,null,0.0,0.0,0.21100226073851,0.0,0.0,null,null,null,0.0,0.0,null,0.0,0.36318407960199,0.0378,null,0.0,null,0.0,null,0.0,1.11,0.0,41182.0,null,null,null,1.05],["2008-12-31",0.0,0.06,0.7962,0.0,0.0,0.0,0.0,0.25119316754584,0.0,0.0,0.0,0.0,0.0,0.0,0.0,null,0.0,0.74269005847953,0.0873,0.0,0.0,0.0,0.0,null,null,0.85,0.0,3500.0,null,null,null,1.25],["2007-12-31",0.0,0.06,0.7962,0.0,0.0,0.0,0.0,0.18085908063301,0.0,0.0,0.0,0.0,0.0,0.0,0.0,null,0.0,0.23954372623574,0.0055,0.0,0.0,0.0,0.0,null,null,2.9,0.0,37780.0,null,null,null,0.9]]}