{"errors":{},"id":3750591,"source_code":"OFDP","source_name":"Open Financial Data Project","code":"DMDRN_CEO_ALLFINANCIALRATIOS","name":"Cnooc Limited ( CEO ) - All Financial Ratios","urlize_name":"Cnooc-Limited-CEO-All-Financial-Ratios","description":"Corporate Finance data is collected and calculated by Prof. Aswath\nDamodaran, Professor of Finance at the Stern School of Business, New\nYork University.  The raw data is available here:\nhttp://pages.stern.nyu.edu/~adamodar/New_Home_Page/data.html","updated_at":"2013-12-28T08:44:55Z","frequency":"annual","from_date":"2002-12-31","to_date":"2004-12-31","column_names":["Date","Number of Shares Outstanding","3-Year Regression Beta","3-year Standard Deviation of Stock Price","Book Debt to Capital Ratio","Book Value of Assets","Capital Expenditures","Cash","Cash as Percentage of Firm Value","Cash as Percentage of Revenues","Change in Non-Cash Working Capital","Correlation with the Market","Current PE Ratio","Depreciation","Dividend Yield","Dividends","Earnings Before Interest and Taxes","EBIT for Previous Period","Earnings Before Interest Taxes Depreciation and Amortization","Effective Tax Rate","Enterprise Value","EV to EBIT Ratio","EV to EBITDA Ratio","EV To Sales Ratio","Free Cash Flow to Firm","Firm Value","Ratio of Fixed Assets to Total Assets","Previous Year Growth in Revenues","Hi-Lo Risk","Insider Holdings","Institutional Holdings","Ratio of Intangible Assets to Total Assets","Invested Capital","Market Capitalization","Market Debt to Equity Ratio","Market Debt to Capital Ratio","Net Income","Net Margin","Non-Cash Working Capital","Non-Cash Working Capital as Percentage of Revenues","Payout Ratio","Price to Book Value Ratio","Pre-Tax Operating Margin","Price to Sales Ratio","Reinvestment Amount","Reinvestment Rate","Revenues","Return on Capital","Return on Equity","Sales General and Administration Expenses","Stock Price","Total Debt","Trading Volume","Trailing 12-month Revenues","Trailing Net Income","Trailing Revenues","Value Line Beta","EV to Book Value Ratio"],"private":false,"type":null,"display_url":"http://pages.stern.nyu.edu/~adamodar/New_Home_Page/data.html","data":[["2004-12-31",0.0,-1.19,2.4598,null,0.0,0.0,0.0,null,null,0.0,-0.096755833807627,null,0.0,0.0,0.0,null,null,null,0.0,0.0,null,null,null,null,0.0,null,0.0,0.26298875200857,null,0.0158,null,0.0,0.0,null,null,0.0,null,0.0,null,null,null,null,null,0.0,null,null,null,null,0.0,53.28,0.0,25300.0,null,0.0,0.0,0.65,null],["2003-12-31",327.9,0.0,0.0,0.32213713887922,3937.8,532.0,751.5,0.048742362723605,0.25980087118855,-85.1,0.0,11.651632095192,311.4,0.016290581895213,236.088,1574.4,1326.306,1885.8,0.15758,14666.3,9.3154852642276,7.7772298228868,5.070282790569,1105.706,15417.8,0.69495657473716,0.4413,0.30631007104053,null,0.0197,0.0,2121.5,14492.3,0.063861498864915,0.060028019561805,1243.8,0.42999377722464,-314.6,-0.10876028486483,0.18981186685962,7.4414890885751,0.54428541796308,5.0101292954435,220.6,0.16632661845481,2892.6,0.62517372048079,0.6386649550706,55.1,44.35,925.5,75741.0,0.0,null,0.0,0.6,6.9131746405845],["2002-12-31",null,null,null,0.3221,3937.8,532.0,751.5,0.077035047615143,0.25980087118855,0.0,null,7.0990512944203,311.4,0.0105,92.7129,1885.8286,1588.6597,2197.2286,0.15758,9003.8,4.7744529911149,4.0977984721298,3.1127013759248,1368.0597,9755.3,0.69495657473716,0.4413,0.2295969520754,0.0,0.0185,0.0,2121.4651,8829.8,0.1048155111101,0.094871505745595,1243.8,0.42999377722464,-314.638,-0.10877342183503,0.074540038591413,4.5339152759949,0.54921514527138,3.0525478807993,220.6,0.1388591879958,null,0.74885027767461,0.6386649550706,55.1,26.4,925.5,9900.0,2892.6,0.0,0.0,null,4.5983787336403]]}